fluviopy/__init__.py
fluviopy/core.py
fluviopy-0.0.2.dist-info/licenses/LICENSE
fluviopy-0.0.2.dist-info/METADATA
fluviopy-0.0.2.dist-info/WHEEL
fluviopy-0.0.2.dist-info/top_level.txt
fluviopy-0.0.2.dist-info/RECORD
