Metadata-Version: 2.4
Name: fluviopy
Version: 0.0.2
Summary: Python library for hydrological analysis
Home-page: https://github.com/jefersonschreiner/FluvioPy.git
Author: Jeferson Schreiner Junior
Author-email: jeferson.schreiner@hotmail.com
Classifier: Programming Language :: Python :: 3
Classifier: License :: OSI Approved :: MIT License
Classifier: Operating System :: OS Independent
Requires-Python: >=3.6
License-File: LICENSE
Requires-Dist: numpy
Requires-Dist: matplotlib
Requires-Dist: scipy
Dynamic: author
Dynamic: author-email
Dynamic: classifier
Dynamic: description
Dynamic: description-content-type
Dynamic: home-page
Dynamic: license-file
Dynamic: requires-dist
Dynamic: requires-python
Dynamic: summary
